{"VRoidStudioVersion":"0.14.0","print_textures":["00#GLB.png","06#GLB.png","11#GLB.png","16#GLB.png","21#GLB.png","26#GLB.png","31#GLB.png","36#GLB.png","41#GLB.png","46#GLB.png","51#GLB.png","56#GLB.png","61#GLB.png","66#GLB.png","71#GLB.png","76#GLB.png","81#GLB.png","86#GLB.png","91#GLB.png"],"blendshape_list":["Face.M_F00_000_00_Fcl_ALL_Neutral","Face.M_F00_000_00_Fcl_ALL_Angry","Face.M_F00_000_00_Fcl_ALL_Fun","Face.M_F00_000_00_Fcl_ALL_Joy","Face.M_F00_000_00_Fcl_ALL_Sorrow","Face.M_F00_000_00_Fcl_ALL_Surprised","Face.M_F00_000_00_Fcl_BRW_Angry","Face.M_F00_000_00_Fcl_BRW_Fun","Face.M_F00_000_00_Fcl_BRW_Joy","Face.M_F00_000_00_Fcl_BRW_Sorrow","Face.M_F00_000_00_Fcl_BRW_Surprised","Face.M_F00_000_00_Fcl_EYE_Natural","Face.M_F00_000_00_Fcl_EYE_Angry","Face.M_F00_000_00_Fcl_EYE_Close","Face.M_F00_000_00_Fcl_EYE_Close_R","Face.M_F00_000_00_Fcl_EYE_Close_L","Face.M_F00_000_00_Fcl_Eye_Fun","Face.M_F00_000_00_Fcl_EYE_Joy","Face.M_F00_000_00_Fcl_EYE_Joy_R","Face.M_F00_000_00_Fcl_EYE_Joy_L","Face.M_F00_000_00_Fcl_EYE_Sorrow","Face.M_F00_000_00_Fcl_EYE_Surprised","Face.M_F00_000_00_Fcl_EYE_Spread","Face.M_F00_000_00_Fcl_EYE_Iris_Hide","Face.M_F00_000_00_Fcl_EYE_Highlight_Hide","Face.M_F00_000_00_Fcl_EYE_Extra","Face.M_F00_000_00_Fcl_MTH_Up","Face.M_F00_000_00_Fcl_MTH_Down","Face.M_F00_000_00_Fcl_MTH_Angry","Face.M_F00_000_00_Fcl_MTH_Neutral","Face.M_F00_000_00_Fcl_MTH_Fun","Face.M_F00_000_00_Fcl_MTH_Joy","Face.M_F00_000_00_Fcl_MTH_Sorrow","Face.M_F00_000_00_Fcl_MTH_Surprised","Face.M_F00_000_00_Fcl_MTH_SkinFung","Face.M_F00_000_00_Fcl_MTH_SkinFung_R","Face.M_F00_000_00_Fcl_MTH_SkinFung_L","Face.M_F00_000_00_Fcl_MTH_A","Face.M_F00_000_00_Fcl_MTH_I","Face.M_F00_000_00_Fcl_MTH_U","Face.M_F00_000_00_Fcl_MTH_E","Face.M_F00_000_00_Fcl_MTH_O","Face.M_F00_000_00_Fcl_HA_Hide","Face.M_F00_000_00_Fcl_HA_Fung1","Face.M_F00_000_00_Fcl_HA_Fung1_Low","Face.M_F00_000_00_Fcl_HA_Fung1_Up","Face.M_F00_000_00_Fcl_HA_Fung2","Face.M_F00_000_00_Fcl_HA_Fung2_Low","Face.M_F00_000_00_Fcl_HA_Fung2_Up","Face.M_F00_000_00_Fcl_HA_Fung3","Face.M_F00_000_00_Fcl_HA_Fung3_Up","Face.M_F00_000_00_Fcl_HA_Fung3_Low","Face.M_F00_000_00_Fcl_HA_Short","Face.M_F00_000_00_Fcl_HA_Short_Up","Face.M_F00_000_00_Fcl_HA_Short_Low","EyeExtra_01.M_F00_000_00_EyeExtra_On"],"blendshape_value":{"Face.M_F00_000_00_Fcl_ALL_Neutral":0,"Face.M_F00_000_00_Fcl_ALL_Angry":0,"Face.M_F00_000_00_Fcl_ALL_Fun":0,"Face.M_F00_000_00_Fcl_ALL_Joy":0,"Face.M_F00_000_00_Fcl_ALL_Sorrow":0,"Face.M_F00_000_00_Fcl_ALL_Surprised":0,"Face.M_F00_000_00_Fcl_BRW_Angry":0,"Face.M_F00_000_00_Fcl_BRW_Fun":0,"Face.M_F00_000_00_Fcl_BRW_Joy":0,"Face.M_F00_000_00_Fcl_BRW_Sorrow":0,"Face.M_F00_000_00_Fcl_BRW_Surprised":0,"Face.M_F00_000_00_Fcl_EYE_Natural":0,"Face.M_F00_000_00_Fcl_EYE_Angry":0,"Face.M_F00_000_00_Fcl_EYE_Close":0,"Face.M_F00_000_00_Fcl_EYE_Close_R":0,"Face.M_F00_000_00_Fcl_EYE_Close_L":0,"Face.M_F00_000_00_Fcl_Eye_Fun":0,"Face.M_F00_000_00_Fcl_EYE_Joy":0,"Face.M_F00_000_00_Fcl_EYE_Joy_R":0,"Face.M_F00_000_00_Fcl_EYE_Joy_L":0,"Face.M_F00_000_00_Fcl_EYE_Sorrow":0,"Face.M_F00_000_00_Fcl_EYE_Surprised":0,"Face.M_F00_000_00_Fcl_EYE_Spread":0,"Face.M_F00_000_00_Fcl_EYE_Iris_Hide":0,"Face.M_F00_000_00_Fcl_EYE_Highlight_Hide":0,"Face.M_F00_000_00_Fcl_EYE_Extra":0,"Face.M_F00_000_00_Fcl_MTH_Up":0,"Face.M_F00_000_00_Fcl_MTH_Down":0,"Face.M_F00_000_00_Fcl_MTH_Angry":0,"Face.M_F00_000_00_Fcl_MTH_Neutral":0,"Face.M_F00_000_00_Fcl_MTH_Fun":0,"Face.M_F00_000_00_Fcl_MTH_Joy":0,"Face.M_F00_000_00_Fcl_MTH_Sorrow":0,"Face.M_F00_000_00_Fcl_MTH_Surprised":0,"Face.M_F00_000_00_Fcl_MTH_SkinFung":0,"Face.M_F00_000_00_Fcl_MTH_SkinFung_R":0,"Face.M_F00_000_00_Fcl_MTH_SkinFung_L":0,"Face.M_F00_000_00_Fcl_MTH_A":0,"Face.M_F00_000_00_Fcl_MTH_I":0,"Face.M_F00_000_00_Fcl_MTH_U":0,"Face.M_F00_000_00_Fcl_MTH_E":0,"Face.M_F00_000_00_Fcl_MTH_O":0,"Face.M_F00_000_00_Fcl_HA_Hide":0,"Face.M_F00_000_00_Fcl_HA_Fung1":0,"Face.M_F00_000_00_Fcl_HA_Fung1_Low":0,"Face.M_F00_000_00_Fcl_HA_Fung1_Up":0,"Face.M_F00_000_00_Fcl_HA_Fung2":0,"Face.M_F00_000_00_Fcl_HA_Fung2_Low":0,"Face.M_F00_000_00_Fcl_HA_Fung2_Up":0,"Face.M_F00_000_00_Fcl_HA_Fung3":0,"Face.M_F00_000_00_Fcl_HA_Fung3_Up":0,"Face.M_F00_000_00_Fcl_HA_Fung3_Low":0,"Face.M_F00_000_00_Fcl_HA_Short":0,"Face.M_F00_000_00_Fcl_HA_Short_Up":0,"Face.M_F00_000_00_Fcl_HA_Short_Low":0,"EyeExtra_01.M_F00_000_00_EyeExtra_On":0}}